setup.py
django_url_history.egg-info/PKG-INFO
django_url_history.egg-info/SOURCES.txt
django_url_history.egg-info/dependency_links.txt
django_url_history.egg-info/requires.txt
django_url_history.egg-info/top_level.txt
url_history/__init__.py
url_history/middleware.py
url_history/models.py
url_history/tests.py
url_history/urls.py
url_history/views.py