Metadata-Version: 1.0
Name: django-url-history
Version: 1.0.0
Summary: Store the last few URLs visited in the session to aid debugging
Home-page: http://github.com/brightinteractive/django-url-history/
Author: Bright Interactive
Author-email: francis@bright-interactive.co.uk
License: BSD
Platform: UNKNOWN
